B3_Propagation-0.1.2.dist-info/METADATA
B3_Propagation-0.1.2.dist-info/RECORD
B3_Propagation-0.1.2.dist-info/WHEEL
B3_Propagation-0.1.2.dist-info/top_level.txt
B3_Propagation-0.1.2.dist-info/zip-safe
b3/__init__.py
