Metadata-Version: 2.1
Name: B3-Propagation
Version: 0.1.2
Summary: B3 header access and propagation for Python.
Home-page: https://github.com/davidcarboni/B3-Propagation
Author: David Carboni
Author-email: david@carboni.io
License: MIT
Keywords: logging,b3,distributed,tracing,zipkin
Platform: UNKNOWN
Classifier: Development Status :: 4 - Beta
Classifier: Programming Language :: Python :: 2.7
Classifier: Programming Language :: Python :: 3.2
Classifier: Topic :: System :: Logging
Classifier: Topic :: Internet :: Log Analysis
Classifier: Intended Audience :: Developers
Classifier: License :: OSI Approved :: MIT License
